{
  "request": {
    "topic": "How Artificial Intelligence is Transforming Manufacturing Excellence",
    "audience": "Global manufacturing leaders, plant managers, and engineering teams",
    "occasion": "BMW Group Global Manufacturing Summit 2026 – Opening Keynote",
    "time_limit_minutes": 6
  },

  "targets": {
    "estimated_wpm": 140,
    "target_word_count": 840
  },

  "sections": [
    {
      "section_id": "S1",
      "name": "Hook",
      "purpose": "Open with a vivid shop-floor moment that contrasts uncertainty with precision, then connect it to AI-enabled manufacturing excellence.",
      "must_include_points": [
        "A concrete, sensory manufacturing scene",
        "A one-line thesis that links AI to excellence"
      ]
    },
    {
      "section_id": "S2",
      "name": "The impact of AI",
      "purpose": "Explain how AI has aided smart manufacturing",
      "must_include_points": [
        "Smart manufacturing has raised productivity by 70%",
        "Singapore has modernized in the past to our benefit, becoming one of the 4 Asian Tigers."
      ]
    },
    {
      "section_id": "S3",
      "name": "Workforce concerns and upskilling",
      "purpose": "Address fears: AI changes jobs; it should elevate people, require training, and improve safety.",
      "must_include_points": [
        "Acknowledge concerns",
        "Explain how roles shift",
        "Commitment to upskilling"
      ]
    },
    {
      "section_id": "S4",
      "name": "Call-to-action and closing",
      "purpose": "End with a forward-looking call: scale responsibly, measure impact, invest in people, and build the next era of manufacturing excellence.",
      "must_include_points": [
        "Forward-looking call-to-action",
        "Memorable closing line"
      ]
    }
  ]
}